pylocked/__init__.py
pylocked/_version.py
pylocked/asyncio.py
pylocked/threading.py
pylocked-1.0.0.dist-info/LICENSE
pylocked-1.0.0.dist-info/METADATA
pylocked-1.0.0.dist-info/WHEEL
pylocked-1.0.0.dist-info/top_level.txt
pylocked-1.0.0.dist-info/RECORD
