Metadata-Version: 2.1
Name: pylocked
Version: 1.0.0
Summary: pylocked provides utility classes (and functions) to lock any resource (or function) and thus make them thread and / or concurrency safe.
Author-email: Eyal Halpern Shalev <eyalsh@gmail.com>
Project-URL: homepage, https://Eyal-Shalev.github.io/pylocked
Project-URL: documentation, https://Eyal-Shalev.github.io/pylocked
Project-URL: repository, https://github.com/Eyal-Shalev/pylocked
Project-URL: issues, https://github.com/Eyal-Shalev/pylocked/issues
Requires-Python: >=3.10
License-File: LICENSE
Provides-Extra: build
Requires-Dist: build (~=0.9) ; extra == 'build'
Requires-Dist: semver (~=2.13) ; extra == 'build'
Provides-Extra: dev
Requires-Dist: pylocked[build,doc,publish,test] ; extra == 'dev'
Requires-Dist: ipython (~=8.6) ; extra == 'dev'
Provides-Extra: docs
Requires-Dist: pdoc (~=12.3) ; extra == 'docs'
Provides-Extra: publish
Requires-Dist: twine (~=4.0) ; extra == 'publish'
Provides-Extra: test
Requires-Dist: pytest (~=7.2) ; extra == 'test'
Requires-Dist: pytest-asyncio (~=0.20) ; extra == 'test'
Requires-Dist: black (~=22.10) ; extra == 'test'
Requires-Dist: mypy (~=0.990) ; extra == 'test'
Requires-Dist: isort (~=5.10) ; extra == 'test'
